Metadata-Version: 2.1
Name: scocli
Version: 1.2
Summary: CLI to facilitate the creation and management of SCORM packages
Home-page: https://github.com/Vasapg/SCO/tree/main
Author: Vasapg
